Metadata-Version: 2.1
Name: apistellar
Version: 1.3.12
Summary: enhance apistar web framework. 
Home-page: https://www.github.com/ShichaoMa/apistellar
Author: cn
Author-email: cnaafhvk@foxmail.com
License: MIT
Keywords: apistar
Platform: UNKNOWN
Classifier: License :: OSI Approved :: MIT License
Classifier: Programming Language :: Python :: 3.6
Classifier: Intended Audience :: Developers
Classifier: Operating System :: Unix
